sphinxcontrib_bitfield-2.0.0-py3.12-nspkg.pth
sphinxcontrib/bitfield.py
sphinxcontrib_bitfield-2.0.0.dist-info/METADATA
sphinxcontrib_bitfield-2.0.0.dist-info/WHEEL
sphinxcontrib_bitfield-2.0.0.dist-info/namespace_packages.txt
sphinxcontrib_bitfield-2.0.0.dist-info/top_level.txt
sphinxcontrib_bitfield-2.0.0.dist-info/RECORD
